{"total": {"lines":{"total":76,"covered":5,"skipped":0,"pct":6.58},"statements":{"total":76,"covered":5,"skipped":0,"pct":6.58},"functions":{"total":48,"covered":4,"skipped":0,"pct":8.33},"branches":{"total":14,"covered":2,"skipped":0,"pct":14.29}}
,"/Users/johannschwabe/Documents/git/ASEv3/frontend/src/components/PropertyCard.vue": {"lines":{"total":6,"covered":5,"skipped":0,"pct":83.33},"functions":{"total":4,"covered":4,"skipped":0,"pct":100},"statements":{"total":6,"covered":5,"skipped":0,"pct":83.33},"branches":{"total":4,"covered":2,"skipped":0,"pct":50}}
,"/Users/johannschwabe/Documents/git/ASEv3/frontend/src/components/map/Heatmap.vue": {"lines":{"total":42,"covered":0,"skipped":0,"pct":0},"functions":{"total":22,"covered":0,"skipped":0,"pct":0},"statements":{"total":42,"covered":0,"skipped":0,"pct":0},"branches":{"total":2,"covered":0,"skipped":0,"pct":0}}
,"/Users/johannschwabe/Documents/git/ASEv3/frontend/src/components/menu/MenuBar.vue": {"lines":{"total":2,"covered":0,"skipped":0,"pct":0},"functions":{"total":2,"covered":0,"skipped":0,"pct":0},"statements":{"total":2,"covered":0,"skipped":0,"pct":0},"branches":{"total":0,"covered":0,"skipped":0,"pct":100}}
,"/Users/johannschwabe/Documents/git/ASEv3/frontend/src/components/menu/MenuDrawer.vue": {"lines":{"total":6,"covered":0,"skipped":0,"pct":0},"functions":{"total":6,"covered":0,"skipped":0,"pct":0},"statements":{"total":6,"covered":0,"skipped":0,"pct":0},"branches":{"total":2,"covered":0,"skipped":0,"pct":0}}
,"/Users/johannschwabe/Documents/git/ASEv3/frontend/src/pages/MainPage.vue": {"lines":{"total":12,"covered":0,"skipped":0,"pct":0},"functions":{"total":6,"covered":0,"skipped":0,"pct":0},"statements":{"total":12,"covered":0,"skipped":0,"pct":0},"branches":{"total":6,"covered":0,"skipped":0,"pct":0}}
,"/Users/johannschwabe/Documents/git/ASEv3/frontend/src/store/actions.js": {"lines":{"total":2,"covered":0,"skipped":0,"pct":0},"functions":{"total":2,"covered":0,"skipped":0,"pct":0},"statements":{"total":2,"covered":0,"skipped":0,"pct":0},"branches":{"total":0,"covered":0,"skipped":0,"pct":100}}
,"/Users/johannschwabe/Documents/git/ASEv3/frontend/src/store/getters.js": {"lines":{"total":3,"covered":0,"skipped":0,"pct":0},"functions":{"total":3,"covered":0,"skipped":0,"pct":0},"statements":{"total":3,"covered":0,"skipped":0,"pct":0},"branches":{"total":0,"covered":0,"skipped":0,"pct":100}}
,"/Users/johannschwabe/Documents/git/ASEv3/frontend/src/store/mutations.js": {"lines":{"total":3,"covered":0,"skipped":0,"pct":0},"functions":{"total":3,"covered":0,"skipped":0,"pct":0},"statements":{"total":3,"covered":0,"skipped":0,"pct":0},"branches":{"total":0,"covered":0,"skipped":0,"pct":100}}
,"/Users/johannschwabe/Documents/git/ASEv3/frontend/src/store/state.js": {"lines":{"total":0,"covered":0,"skipped":0,"pct":0},"functions":{"total":0,"covered":0,"skipped":0,"pct":0},"statements":{"total":0,"covered":0,"skipped":0,"pct":0},"branches":{"total":0,"covered":0,"skipped":0,"pct":0}}
}
